.DS_Store
kpfm/__init__.py
kpfm/_version.py
kpfm/lockin/__init__.py
kpfm/pkefm/__init__.py
kpfm/pkefm/_report.py
kpfm/pkefm/_version.py
kpfm/pkefm/phasekick.py
kpfm/scratch/__init__.py
kpfm/scratch/timedomain1703.py
kpfm/tests/__init__.py
kpfm/tests/test_kpfm.py
kpfm/tests/test_lockin.py
kpfm/tests/test_util.py
kpfm/util/__init__.py
kpfm/util/readtxt.py
kpfm-0.3.dist-info/DESCRIPTION.rst
kpfm-0.3.dist-info/METADATA
kpfm-0.3.dist-info/RECORD
kpfm-0.3.dist-info/WHEEL
kpfm-0.3.dist-info/metadata.json
kpfm-0.3.dist-info/top_level.txt
