Metadata-Version: 2.0
Name: kpfm
Version: 0.3
Summary: Kelvin Probe Force Microscopy (KPFM) signal processing utilities.
Home-page: https://github.com/ryanpdwyer/kpfm
Author: Ryan Dwyer
Author-email: ryanpdwyer@gmail.com
License: MIT
Keywords: kpfm
Platform: UNKNOWN
Classifier: Development Status :: 2 - Pre-Alpha
Classifier: License :: OSI Approved :: MIT License
Classifier: Natural Language :: English
Classifier: Programming Language :: Python :: 2
Classifier: Programming Language :: Python :: 2.7
Requires-Dist: decorator
Requires-Dist: decorator
Requires-Dist: munch
Requires-Dist: sigutils
Requires-Dist: six
Requires-Dist: tqdm
